conjurer/__init__.py
conjurer/eda.py
conjurer/ml.py
conjurer/logic/__init__.py
conjurer/logic/eda/__init__.py
conjurer/logic/eda/check/__init__.py
conjurer/logic/eda/check/alert.py
conjurer/logic/eda/check/api.py
conjurer/logic/eda/check/stat_calculator.py
conjurer/logic/eda/load/__init__.py
conjurer/logic/eda/load/df_dict_loader.py
conjurer/logic/eda/load/pandas_csv.py
conjurer/logic/eda/reformat/__init__.py
conjurer/logic/eda/reformat/table_transformer.py
conjurer/logic/eda/utils/__init__.py
conjurer/logic/eda/utils/subprocess_wrapper.py
conjurer/logic/eda/vis/__init__.py
conjurer/logic/eda/vis/binning.py
conjurer/logic/eda/vis/histogram.py
conjurer/logic/eda/vis/scatter.py
conjurer/logic/eda/vis/theme.py
conjurer/logic/ml/__init__.py
conjurer/logic/ml/tuner/__init__.py
conjurer/logic/ml/tuner/cv_analyzer.py
conjurer/logic/ml/tuner/ml_tuner.py
conjurer/logic/ml/tuner/tuner_config/__init__.py
conjurer/logic/ml/tuner/tuner_config/base.py
conjurer/logic/ml/tuner/tuner_config/lightgbm.py
conjurer/logic/ml/tuner/tuner_config/linear_model.py
conjurer/logic/ml/tuner/tuner_config/random_forest.py
conjurer/logic/ml/tuner/tuner_config/xgboost.py
conjurer/logic/ml/tuner/tuner_config/utils/__init__.py
conjurer/logic/ml/tuner/tuner_config/utils/make_pipeline.py
conjurer-0.0.24.dist-info/METADATA
conjurer-0.0.24.dist-info/WHEEL
conjurer-0.0.24.dist-info/top_level.txt
conjurer-0.0.24.dist-info/RECORD
