Metadata-Version: 2.1
Name: conjurer
Version: 0.0.24
Summary: Python library to help you to perform magic on your data analytics project
Home-page: https://github.com/not-so-fat/conjurer
Author: @not-so-fat
Author-email: conjurer.not.so.fat@gmail.com
Classifier: Programming Language :: Python :: 3
Classifier: License :: OSI Approved :: MIT License
Classifier: Operating System :: OS Independent
Requires-Python: >=3.6
Requires-Dist: numpy
Requires-Dist: scipy
Requires-Dist: altair
Requires-Dist: IPython
Requires-Dist: gbm-autosplit (>=0.0.10)
Requires-Dist: sklearn-cv-pandas (>=0.0.11)
